Metadata-Version: 2.1
Name: midi2Tiles
Version: 1.0.1
Summary: Create synthesia-like piano tiles effect from midi files.
Home-page: https://github.com/atosystem/midi2Tiles
Author: atosystem
Author-email: yjshih23@gmail.com
License: MIT
Keywords: synthesia,midi,music,video,animation,matplotlib
Platform: UNKNOWN
